setup.py
print437437/__init__.py
print437437/temp.py
print437437.egg-info/PKG-INFO
print437437.egg-info/SOURCES.txt
print437437.egg-info/dependency_links.txt
print437437.egg-info/requires.txt
print437437.egg-info/top_level.txt