Metadata-Version: 2.1
Name: print437437
Version: 0.0.1
Summary: chuan's private utils.
Home-page: https://github.com/chuan
Author: chuan
Author-email: wangchuan437@126.com
License: MIT Licence
Keywords: pip,print437437
Platform: any
Requires-Dist: numpy
Requires-Dist: pillow
